DjangoMpesa/__init__.py
DjangoMpesa/settings.py
DjangoMpesa/urls.py
DjangoMpesa/wsgi.py
mpesaApp/__init__.py
mpesaApp/admin.py
mpesaApp/api.py
mpesaApp/apps.py
mpesaApp/models.py
mpesaApp/tasks.py
mpesaApp/tests.py
mpesaApp/urls.py
mpesaApp/utils.py
mpesaApp/views.py
DjangoMpesa-2.2.dist-info/LICENSE.md
DjangoMpesa-2.2.dist-info/METADATA
DjangoMpesa-2.2.dist-info/WHEEL
DjangoMpesa-2.2.dist-info/top_level.txt
DjangoMpesa-2.2.dist-info/RECORD
