Metadata-Version: 2.1
Name: DjangoMpesa
Version: 2.2
Summary: A simple Django app for integrating mpesa stk push payment to your django site.
Home-page: http://www.techtenant.co.ke/
Author: Oronz
Author-email: brianoroni6@gmail.com
License: BSD License
Keywords: MPESA,Django,Djangompesa
Platform: UNKNOWN
Classifier: Environment :: Web Environment
Classifier: Framework :: Django
Classifier: Intended Audience :: Developers
Classifier: License :: OSI Approved :: BSD License
Classifier: Operating System :: OS Independent
Classifier: Programming Language :: Python
Classifier: Programming Language :: Python :: 3.8
Requires-Python: >=3.6
Requires-Dist: celery (==4.3.0)
Requires-Dist: kombu (==4.6.8)
Requires-Dist: redis (==3.5.2)
Requires-Dist: requests (==2.21.0)
Requires-Dist: django-celery-beat (==1.1.1)
